core_scripts/__init__.py
core_scripts/browse_history/api/Browser.py
core_scripts/browse_history/api/Chrome.py
core_scripts/browse_history/api/util.py
core_scripts/browse_history/browse-.py
core_scripts/browse_history/example.json
core_scripts/browse_history/info.txt
core_scripts/browse_history/learn.txt
core_scripts/browse_history/main.py
core_scripts/browse_history/TODO.txt
core_scripts/browse_history/vars.py
core_scripts/fileSystem/!change_extension.py
core_scripts/fileSystem/!check_extension.py
core_scripts/fileSystem/!check_name.py
core_scripts/fileSystem/!compress_all.py
core_scripts/fileSystem/!compress_all_dirs_.py
core_scripts/fileSystem/!compress_all_dirs_in_list.py
core_scripts/fileSystem/!compress_only_dirs.py
core_scripts/fileSystem/!create_html.py
core_scripts/fileSystem/!create_json.py
core_scripts/fileSystem/!create_md.py
core_scripts/fileSystem/!create_sql.py
core_scripts/fileSystem/!create_xml.py
core_scripts/fileSystem/!create_yaml.py
core_scripts/fileSystem/!formatFiles.py
core_scripts/fileSystem/!get_metadata.py
core_scripts/fileSystem/!get_metadata_timestramp.py
core_scripts/fileSystem/!get_name.py
core_scripts/fileSystem/!make-dir.py
core_scripts/fileSystem/!numeric_secuence.py
core_scripts/fileSystem/!read_toml.py
core_scripts/fileSystem/!rename.py
core_scripts/fileSystem/!rename_alfabeticSequence.py
core_scripts/fileSystem/!rename_alfanumericSequence.py
core_scripts/fileSystem/!rename_insertBeganing.py
core_scripts/fileSystem/!rename_insertEnd.py
core_scripts/fileSystem/!rename_insertIn.py
core_scripts/fileSystem/!rename_numericSequence.py
core_scripts/fileSystem/!take_customDir.py
core_scripts/fileSystem/!take_first_custom_folder.py
core_scripts/fileSystem/!takeFirst_dir.py
core_scripts/fileSystem/!takeFirst_namedDir.py
core_scripts/fileSystem/__init__.py
core_scripts/fileSystem/create_file.py
core_scripts/fileSystem/create_lock.py
core_scripts/fileSystem/create_toml.py
core_scripts/fileSystem/download_gallery.py
core_scripts-0.4.3.dist-info/METADATA
core_scripts-0.4.3.dist-info/WHEEL
core_scripts-0.4.3.dist-info/RECORD
